configmanager_hjy/__init__.py
configmanager_hjy/core/__init__.py
configmanager_hjy/core/manager.py
configmanager_hjy-0.3.0.dist-info/licenses/LICENSE
configmanager_hjy-0.3.0.dist-info/METADATA
configmanager_hjy-0.3.0.dist-info/WHEEL
configmanager_hjy-0.3.0.dist-info/top_level.txt
configmanager_hjy-0.3.0.dist-info/RECORD
