Metadata-Version: 2.4
Name: configmanager-hjy
Version: 0.3.0
Summary: 统一配置管理包 - 配置的云原生大脑
Author-email: hjy <hjy@example.com>
Maintainer-email: hjy <hjy@example.com>
License: MIT
Project-URL: Homepage, https://github.com/hjy/configmanager-hjy
Project-URL: Documentation, https://github.com/hjy/configmanager-hjy#readme
Project-URL: Repository, https://github.com/hjy/configmanager-hjy.git
Project-URL: Bug Tracker, https://github.com/hjy/configmanager-hjy/issues
Keywords: config,management,cloud-native,database,redis,oss
Classifier: Development Status :: 3 - Alpha
Classifier: Intended Audience :: Developers
Classifier: License :: OSI Approved :: MIT License
Classifier: Operating System :: OS Independent
Classifier: Programming Language :: Python :: 3
Classifier: Programming Language :: Python :: 3.8
Classifier: Programming Language :: Python :: 3.9
Classifier: Programming Language :: Python :: 3.10
Classifier: Programming Language :: Python :: 3.11
Classifier: Programming Language :: Python :: 3.12
Classifier: Programming Language :: Python :: 3.13
Classifier: Topic :: Software Development :: Libraries :: Python Modules
Classifier: Topic :: System :: Systems Administration
Requires-Python: >=3.8
License-File: LICENSE
Requires-Dist: pydantic>=2.0.0
Requires-Dist: redis>=4.5.0
Requires-Dist: mysql-connector-python>=8.0.0
Requires-Dist: oss2>=2.18.0
Requires-Dist: pyyaml>=6.0.0
Requires-Dist: loguru>=0.7.0
Provides-Extra: dev
Requires-Dist: pytest>=7.0.0; extra == "dev"
Requires-Dist: pytest-asyncio>=0.21.0; extra == "dev"
Requires-Dist: black>=23.0.0; extra == "dev"
Requires-Dist: isort>=5.12.0; extra == "dev"
Requires-Dist: flake8>=6.0.0; extra == "dev"
Dynamic: license-file
